turtlesc/__init__.py
turtlesc-0.1.0.dist-info/METADATA
turtlesc-0.1.0.dist-info/WHEEL
turtlesc-0.1.0.dist-info/RECORD
