Metadata-Version: 2.4
Name: TurtleSC
Version: 0.1.0
Summary: Make turtle.py function calls with a mini-language of shortcuts, like 'f 100' for forward(100).
Project-URL: Homepage, https://github.com/asweigart/turtlesc
Project-URL: Issues, https://github.com/asweigart/turtlesc/issues
Author-email: Al Sweigart <al@inventwithpython.com>
Classifier: Operating System :: OS Independent
Classifier: Programming Language :: Python :: 2
Classifier: Programming Language :: Python :: 3
Requires-Python: >=2.7
